dekeyrej_securedict-0.9.6.dist-info/licenses/LICENSE
securedict/__init__.py
securedict/decrypt.py
securedict/encrypt.py
dekeyrej_securedict-0.9.6.dist-info/METADATA
dekeyrej_securedict-0.9.6.dist-info/WHEEL
dekeyrej_securedict-0.9.6.dist-info/top_level.txt
dekeyrej_securedict-0.9.6.dist-info/RECORD
