Metadata-Version: 2.4
Name: dekeyrej-securedict
Version: 0.9.6
Summary: value encryption for secrets
Author: J.DeKeyrel
Author-email: "J. DeKeyrel" <noneyabusiness@notemail.com>
License: The MIT License (MIT)
Classifier: License :: OSI Approved :: MIT License
Classifier: Programming Language :: Python
Classifier: Programming Language :: Python :: 3
Requires-Python: >=3.9
License-File: LICENSE
Requires-Dist: cryptography
Requires-Dist: kubernetes
Dynamic: author
Dynamic: license-file
